mapal/__init__.py
mapal/alloy_features/__init__.py
mapal/create_alloys/__init__.py
mapal/element_data/__init__.py
mapal/element_data/mapal_EL1/db_element.json
mapal/element_data/mapal_EL1/db_element_info.json
mapal/map_ML_predictions/__init__.py
mapal/map_features/__init__.py
mapal/miedema_calc/__init__.py
mapal/preTrained_ML_mods/__init__.py
mapal/preTrained_ML_mods/model_info.json
mapal/preTrained_ML_mods/M1-trained-model/mod_feats_input.csv
mapal/preTrained_ML_mods/M1-trained-model/min_max_feat_values/xmax.csv
mapal/preTrained_ML_mods/M1-trained-model/min_max_feat_values/xmin.csv
mapal/preTrained_ML_mods/M1-trained-model/mod_files/1.stop2600_K2_model.h5
mapal/preTrained_ML_mods/M1-trained-model/mod_files/1.stop2700_K1_model.h5
mapal/preTrained_ML_mods/M1-trained-model/mod_files/1.stop3700_K3_model.h5
mapal/preTrained_ML_mods/M1-trained-model/mod_files/1.stop5000_K4_model.h5
mapal/preTrained_ML_mods/M1-trained-model/mod_files/1.stop5000_K5_model.h5
mapal/preTrained_ML_mods/M1-trained-model/mod_files/10.stop1800_K2_model.h5
mapal/preTrained_ML_mods/M1-trained-model/mod_files/10.stop1900_K5_model.h5
mapal/preTrained_ML_mods/M1-trained-model/mod_files/10.stop2300_K4_model.h5
mapal/preTrained_ML_mods/M1-trained-model/mod_files/10.stop2900_K3_model.h5
mapal/preTrained_ML_mods/M1-trained-model/mod_files/10.stop5000_K1_model.h5
mapal/preTrained_ML_mods/M1-trained-model/mod_files/11.stop1200_K2_model.h5
mapal/preTrained_ML_mods/M1-trained-model/mod_files/11.stop2100_K1_model.h5
mapal/preTrained_ML_mods/M1-trained-model/mod_files/11.stop3700_K3_model.h5
mapal/preTrained_ML_mods/M1-trained-model/mod_files/11.stop900_K4_model.h5
mapal/preTrained_ML_mods/M1-trained-model/mod_files/11.stop900_K5_model.h5
mapal/preTrained_ML_mods/M1-trained-model/mod_files/12.stop1000_K3_model.h5
mapal/preTrained_ML_mods/M1-trained-model/mod_files/12.stop1300_K1_model.h5
mapal/preTrained_ML_mods/M1-trained-model/mod_files/12.stop1700_K5_model.h5
mapal-1.1.dist-info/METADATA
mapal-1.1.dist-info/WHEEL
mapal-1.1.dist-info/top_level.txt
mapal-1.1.dist-info/RECORD
