Metadata-Version: 2.1
Name: mapal
Version: 1.1
Summary: MAPping ALloys - A Python library for mapping features and properties of alloys over compositional spaces.
Home-page: https://sites.google.com/view/mapal-pylib
Author: Dishant Beniwal; Pratik K. Ray
Author-email: dishant.beniwal@gmail.com; 
License: MIT
Keywords: mapal; mapping alloys; alloy features; multi-principal element alloys
Requires-Dist: numpy
Requires-Dist: pandas
Requires-Dist: tensorflow
Requires-Dist: matplotlib
Requires-Dist: plotly
Requires-Dist: scikit-image
